shrive-0.1.0.dist-info/METADATA
shrive-0.1.0.dist-info/WHEEL
shrive/__init__.py
shrive/shrive.cp312-win_amd64.pyd
shrive-0.1.0.dist-info/RECORD
