Metadata-Version: 2.4
Name: shrive
Version: 0.1.0
Classifier: Programming Language :: Python :: 3
Classifier: Programming Language :: Rust
Classifier: License :: OSI Approved :: MIT License
Classifier: Operating System :: OS Independent
Summary: A Python package built with Rust using PyO3
Author-email: Kirby <korbinian.brunner@web.de>
License: MIT
Requires-Python: >=3.7
Project-URL: Homepage, https://github.com/JacobKurtzbergsNickname/shrive
Project-URL: Repository, https://github.com/JacobKurtzbergsNickname/shrive
